jupyter_server_signaling/__init__.py
jupyter_server_signaling/app.py
jupyter_server_signaling/handlers.py
jupyter_server_signaling-0.2.1.data/data/etc/jupyter/jupyter_server_config.d/jupyter_shared_drive.json
jupyter_server_signaling-0.2.1.dist-info/METADATA
jupyter_server_signaling-0.2.1.dist-info/WHEEL
jupyter_server_signaling-0.2.1.dist-info/licenses/LICENSE
jupyter_server_signaling-0.2.1.dist-info/RECORD
