Metadata-Version: 2.4
Name: jupyter-server-signaling
Version: 0.2.1
Summary: jupyter-server extension for WebRTC signaling.
Author-email: Jupyter Development Team <jupyter@googlegroups.com>
License: # Licensing terms
License-File: LICENSE
Classifier: Framework :: Jupyter
Classifier: Intended Audience :: Developers
Classifier: Intended Audience :: Science/Research
Classifier: Intended Audience :: System Administrators
Classifier: License :: OSI Approved :: BSD License
Classifier: Programming Language :: Python
Classifier: Programming Language :: Python :: 3.9
Classifier: Programming Language :: Python :: 3.10
Classifier: Programming Language :: Python :: 3.11
Classifier: Programming Language :: Python :: 3.12
Classifier: Programming Language :: Python :: 3.13
Requires-Python: >=3.9
Requires-Dist: jupyter-server<3.0.0,>=2.4.0
Requires-Dist: websockets
